json/__init__.py
pypv/__init__.py
pypv/_range.py
pypv/pv_inverter.py
pypv/pv_module.py
pypv/pv_system.py
pypv/solar_physics.py
pypv/tests/__init__.py
pypv/tests/test_pv_system.py
pypv-0.3.0.dist-info/LICENSE
pypv-0.3.0.dist-info/METADATA
pypv-0.3.0.dist-info/WHEEL
pypv-0.3.0.dist-info/top_level.txt
pypv-0.3.0.dist-info/RECORD
