Metadata-Version: 2.1
Name: pypv
Version: 0.3.0
Summary: pypv is a state-of-the-art Python library designed to empower engineers and developers in the field of solar energy. This library simplifies the use of complex physical models, making it easier to calculate key solar parameters and optimize solar energy systems. 
Home-page: https://github.com/patrickpasquini/PyPv.git
Author: Patrick Pasquini
Author-email: contatopasquini@gmail.com
Keywords: photovoltaic,pv panel,pv inverter,mppt,pv-calculator
Classifier: Development Status :: 3 - Alpha
Classifier: Intended Audience :: Developers
Classifier: Topic :: Software Development :: Build Tools
Classifier: License :: OSI Approved :: MIT License
Classifier: Programming Language :: Python :: 3
Requires-Python: >=3.11
License-File: LICENSE
